{"cameraMode":{"drawMode":2,"name":"Shaded Wireframe","section":"Shading Mode"},"sceneLighting":true,"audioPlay":false,"sceneViewState":{"m_AlwaysRefresh":false,"showFog":true,"showSkybox":true,"showFlares":true,"showImageEffects":true,"showParticleSystems":true,"showVisualEffectGraphs":true,"m_FxEnabled":true},"in2DMode":false,"pivot":{"x":7.025932312011719,"y":18.824085235595704,"z":-15.750089645385743},"rotation":{"x":0.028840750455856324,"y":0.9699273705482483,"z":-0.143878772854805,"w":0.19433361291885377},"size":4.695754528045654,"orthographic":true}